aimigrate/README.md
aimigrate/__init__.py
aimigrate/chat.py
aimigrate/code.py
aimigrate/files.py
aimigrate/migrate_core.py
aimigrate/migrate_diff.py
aimigrate/migrate_oob.py
aimigrate/migrate_repo.py
aimigrate/migration.py
aimigrate/paths.py
aimigrate/utils.py
aimigrate/version.py
aimigrate-0.2.2.dist-info/licenses/LICENSE
aimigrate-0.2.2.dist-info/WHEEL
aimigrate-0.2.2.dist-info/METADATA
aimigrate-0.2.2.dist-info/RECORD
