Metadata-Version: 2.4
Name: aimigrate
Version: 0.2.2
Summary: AI tool for migrating code
Author: Cliff Kerr, Katherine Rosenfeld, Jessica Lundin
Author-email: Starsim Development Team <info@starsim.org>
Requires-Python: >=3.10
License-File: LICENSE
Requires-Dist: aisuite[anthropic, google, ollama, openai]>=0.1.3
Requires-Dist: sciris>=3.2.0
Requires-Dist: tiktoken>=0.8.0
